{"type":"PR","pr":{"number":43,"head":"e56441e8921974ace90a60e8de6cac4e5c542932"},"user":"gally.marco","status":"pending_publish","branch":"cms/posts/2020-01-13-stalker","collection":"posts","commitMessage":"Update Posts “2020-01-13-stalker”","title":"Stalker","description":"«\"La Zona è tutto quello che ho... la sola cosa che mi è rimasta\"»","objects":{"entry":{"path":"_posts/2020-01-13-stalker.md","sha":"bd91e71ad003bbe5ebb809347e5cdce40b2f3e73"},"files":[]},"timeStamp":"2020-01-13T21:14:44.190Z","version":"1"}